{"symbol":"AMZN","fetchedAt":"2026-07-15T20:11:11.453Z","quote":{"price":254.96,"prevClose":247.49,"name":"Amazon.com, Inc.","time":1784145601},"earnTs":1785441600,"divYield":0,"chains":{"1784246400":[{"strike":115,"bid":137.9,"ask":139.65,"impliedVolatility":0.000010000000000000003,"openInterest":818},{"strike":120,"bid":133.1,"ask":135.2,"impliedVolatility":3.6835945410156254,"openInterest":60},{"strike":125,"bid":127.65,"ask":129.75,"impliedVolatility":0.000010000000000000003,"openInterest":80},{"strike":130,"bid":123.35,"ask":126.05,"impliedVolatility":4.225590655517578,"openInterest":61},{"strike":135,"bid":118.4,"ask":121.05,"impliedVolatility":4.016606541748047,"openInterest":49},{"strike":140,"bid":112.95,"ask":115.95,"impliedVolatility":3.7470709448242188,"openInterest":54},{"strike":145,"bid":108,"ask":111.1,"impliedVolatility":3.6523446191406252,"openInterest":63},{"strike":150,"bid":103.2,"ask":105.9,"impliedVolatility":3.3359391601562494,"openInterest":404},{"strike":155,"bid":98.35,"ask":99.95,"impliedVolatility":0.000010000000000000003,"openInterest":177},{"strike":160,"bid":92.9,"ask":94.35,"impliedVolatility":0.000010000000000000003,"openInterest":169},{"strike":165,"bid":88.05,"ask":90.85,"impliedVolatility":2.7851592871093755,"openInterest":182},{"strike":170,"bid":83.4,"ask":85.95,"impliedVolatility":2.6777376806640625,"openInterest":113},{"strike":175,"bid":77.95,"ask":80.3,"impliedVolatility":2.0781298046874994,"openInterest":195},{"strike":180,"bid":72.7,"ask":74.3,"impliedVolatility":0.000010000000000000003,"openInterest":323},{"strike":185,"bid":68.6,"ask":69.5,"impliedVolatility":0.000010000000000000003,"openInterest":372},{"strike":190,"bid":62.75,"ask":64.95,"impliedVolatility":0.000010000000000000003,"openInterest":1105},{"strike":195,"bid":58.4,"ask":60.95,"impliedVolatility":1.9013676806640625,"openInterest":911},{"strike":200,"bid":52.95,"ask":55,"impliedVolatility":1.05859845703125,"openInterest":2764},{"strike":205,"bid":47.95,"ask":50.4,"impliedVolatility":1.36328443359375,"openInterest":1721},{"strike":210,"bid":43.55,"ask":45.05,"impliedVolatility":0.9589847851562499,"openInterest":3554},{"strike":215,"bid":39.05,"ask":39.65,"impliedVolatility":0.000010000000000000003,"openInterest":1928},{"strike":217.5,"bid":36.1,"ask":36.95,"impliedVolatility":0.000010000000000000003,"openInterest":363},{"strike":220,"bid":33.95,"ask":34.5,"impliedVolatility":0.000010000000000000003,"openInterest":5467},{"strike":222.5,"bid":31.1,"ask":31.95,"impliedVolatility":0.000010000000000000003,"openInterest":927},{"strike":225,"bid":28.95,"ask":29.35,"impliedVolatility":0.000010000000000000003,"openInterest":3601},{"strike":227.5,"bid":26.2,"ask":26.8,"impliedVolatility":0.000010000000000000003,"openInterest":875},{"strike":230,"bid":24.1,"ask":24.35,"impliedVolatility":0.000010000000000000003,"openInterest":4678},{"strike":232.5,"bid":21.4,"ask":22.1,"impliedVolatility":0.000010000000000000003,"openInterest":1660},{"strike":235,"bid":19.1,"ask":19.35,"impliedVolatility":0.000010000000000000003,"openInterest":4238},{"strike":237.5,"bid":16.45,"ask":17.25,"impliedVolatility":0.000010000000000000003,"openInterest":1177},{"strike":240,"bid":14.35,"ask":14.45,"impliedVolatility":0.000010000000000000003,"openInterest":14074},{"strike":242.5,"bid":11.85,"ask":12,"impliedVolatility":0.000010000000000000003,"openInterest":4186},{"strike":245,"bid":9.55,"ask":9.75,"impliedVolatility":0.000010000000000000003,"openInterest":27520},{"strike":247.5,"bid":7.35,"ask":7.45,"impliedVolatility":0.000010000000000000003,"openInterest":14132},{"strike":250,"bid":5.5,"ask":5.65,"impliedVolatility":0.2624585473632813,"openInterest":44205},{"strike":252.5,"bid":3.85,"ask":3.95,"impliedVolatility":0.2758861474609374,"openInterest":11234},{"strike":255,"bid":2.58,"ask":2.62,"impliedVolatility":0.28626202026367187,"openInterest":20987},{"strike":257.5,"bid":1.62,"ask":1.64,"impliedVolatility":0.29395237304687494,"openInterest":10631},{"strike":260,"bid":0.99,"ask":1.01,"impliedVolatility":0.30591514404296877,"openInterest":34920},{"strike":262.5,"bid":0.58,"ask":0.6,"impliedVolatility":0.31641308593749995,"openInterest":7563},{"strike":265,"bid":0.33,"ask":0.35,"impliedVolatility":0.327155166015625,"openInterest":24365},{"strike":267.5,"bid":0.19,"ask":0.21,"impliedVolatility":0.3413151806640625,"openInterest":1741},{"strike":270,"bid":0.11,"ask":0.13,"impliedVolatility":0.35645174804687496,"openInterest":27534},{"strike":272.5,"bid":0.07,"ask":0.08,"impliedVolatility":0.3711000390625,"openInterest":181},{"strike":275,"bid":0.05,"ask":0.06,"impliedVolatility":0.39649041015625003,"openInterest":19598},{"strike":277.5,"bid":0.03,"ask":0.05,"impliedVolatility":0.42578699218750005,"openInterest":37},{"strike":280,"bid":0.02,"ask":0.03,"impliedVolatility":0.4335994140625,"openInterest":32329},{"strike":285,"bid":0,"ask":0.01,"impliedVolatility":0.445318046875,"openInterest":15357},{"strike":290,"bid":0,"ask":0.01,"impliedVolatility":0.507817421875,"openInterest":18223},{"strike":295,"bid":0,"ask":0.01,"impliedVolatility":0.5312546875,"openInterest":7792},{"strike":300,"bid":0,"ask":0.01,"impliedVolatility":0.5937540625000001,"openInterest":34000},{"strike":305,"bid":0,"ask":0.01,"impliedVolatility":0.64062859375,"openInterest":9240},{"strike":310,"bid":0,"ask":0.01,"impliedVolatility":0.6875031250000001,"openInterest":6211},{"strike":315,"bid":0,"ask":0.01,"impliedVolatility":0.7500025,"openInterest":4120},{"strike":320,"bid":0,"ask":0.02,"impliedVolatility":0.8437515624999999,"openInterest":10664},{"strike":325,"bid":0,"ask":0.01,"impliedVolatility":0.8437515624999999,"openInterest":2185},{"strike":330,"bid":0,"ask":0.01,"impliedVolatility":0.9062509375,"openInterest":3719},{"strike":335,"bid":0,"ask":0.06,"impliedVolatility":1.109379453125,"openInterest":707},{"strike":340,"bid":0,"ask":0.02,"impliedVolatility":1.0468797656250002,"openInterest":1796},{"strike":345,"bid":0,"ask":0.06,"impliedVolatility":1.21875390625,"openInterest":173},{"strike":350,"bid":0,"ask":0.01,"impliedVolatility":1.09375453125,"openInterest":6053},{"strike":355,"bid":0,"ask":0.06,"impliedVolatility":1.3203158984374999,"openInterest":251},{"strike":360,"bid":0,"ask":0.01,"impliedVolatility":1.1875040625,"openInterest":1785},{"strike":370,"bid":0,"ask":0.01,"impliedVolatility":1.2500037499999999,"openInterest":2671},{"strike":375,"bid":0,"ask":0.06,"impliedVolatility":1.5078149609375,"openInterest":425},{"strike":380,"bid":0,"ask":0.02,"impliedVolatility":1.40625296875,"openInterest":3478}],"1784505600":[{"strike":200,"bid":52.75,"ask":55.95,"impliedVolatility":1.2407264526367183,"openInterest":50},{"strike":210,"bid":43.15,"ask":45.3,"impliedVolatility":0.8339860351562498,"openInterest":93},{"strike":215,"bid":38.5,"ask":39.8,"impliedVolatility":0.000010000000000000003,"openInterest":63},{"strike":230,"bid":23.5,"ask":24.8,"impliedVolatility":0.000010000000000000003,"openInterest":362},{"strike":232.5,"bid":21.05,"ask":22.4,"impliedVolatility":0.000010000000000000003,"openInterest":126},{"strike":235,"bid":18.9,"ask":19.6,"impliedVolatility":0.000010000000000000003,"openInterest":330},{"strike":237.5,"bid":15.95,"ask":17.55,"impliedVolatility":0.28516339843749994,"openInterest":95},{"strike":240,"bid":13.7,"ask":15.2,"impliedVolatility":0.3007882421875,"openInterest":84},{"strike":242.5,"bid":11.65,"ask":12.8,"impliedVolatility":0.28174546386718746,"openInterest":171},{"strike":245,"bid":9.9,"ask":10.25,"impliedVolatility":0.2280350634765625,"openInterest":444},{"strike":247.5,"bid":7.85,"ask":8.25,"impliedVolatility":0.2523268127441406,"openInterest":316},{"strike":250,"bid":6.1,"ask":6.35,"impliedVolatility":0.25489026367187506,"openInterest":799},{"strike":252.5,"bid":4.5,"ask":4.75,"impliedVolatility":0.2602613037109375,"openInterest":586},{"strike":255,"bid":3.25,"ask":3.45,"impliedVolatility":0.2661206201171875,"openInterest":527},{"strike":257.5,"bid":2.29,"ask":2.39,"impliedVolatility":0.26819579467773436,"openInterest":351},{"strike":260,"bid":1.52,"ask":1.62,"impliedVolatility":0.2727123510742187,"openInterest":499},{"strike":262.5,"bid":0.96,"ask":1.08,"impliedVolatility":0.27857166748046874,"openInterest":328},{"strike":265,"bid":0.62,"ask":0.65,"impliedVolatility":0.2771068383789062,"openInterest":167},{"strike":267.5,"bid":0.36,"ask":0.44,"impliedVolatility":0.2880930566406249,"openInterest":147},{"strike":270,"bid":0.24,"ask":0.29,"impliedVolatility":0.2973703076171874,"openInterest":153},{"strike":272.5,"bid":0.08,"ask":0.22,"impliedVolatility":0.31445998046874996,"openInterest":34},{"strike":275,"bid":0.09,"ask":0.12,"impliedVolatility":0.31250687499999996,"openInterest":19},{"strike":280,"bid":0.01,"ask":0.07,"impliedVolatility":0.3437565625,"openInterest":63},{"strike":285,"bid":0,"ask":0.05,"impliedVolatility":0.38086556640624997,"openInterest":24},{"strike":290,"bid":0,"ask":0.13,"impliedVolatility":0.49219257812500006,"openInterest":20},{"strike":300,"bid":0,"ask":0.34,"impliedVolatility":0.62305064453125,"openInterest":4}],"1784678400":[{"strike":210,"bid":43.35,"ask":44.85,"impliedVolatility":0.000010000000000000003,"openInterest":5},{"strike":215,"bid":38.55,"ask":39.9,"impliedVolatility":0.000010000000000000003,"openInterest":17},{"strike":220,"bid":33.55,"ask":34.9,"impliedVolatility":0.000010000000000000003,"openInterest":14},{"strike":225,"bid":28.65,"ask":29.95,"impliedVolatility":0.000010000000000000003,"openInterest":61},{"strike":230,"bid":23.5,"ask":25.1,"impliedVolatility":0.36426416992187505,"openInterest":149},{"strike":232.5,"bid":21.25,"ask":22.7,"impliedVolatility":0.3657289990234375,"openInterest":5},{"strike":237.5,"bid":16.3,"ask":18.05,"impliedVolatility":0.36524072265625,"openInterest":41},{"strike":240,"bid":14.15,"ask":15.8,"impliedVolatility":0.35938140625,"openInterest":486},{"strike":242.5,"bid":12.05,"ask":13.3,"impliedVolatility":0.3154365332031249,"openInterest":45},{"strike":245,"bid":10.5,"ask":11.1,"impliedVolatility":0.3020089331054688,"openInterest":258},{"strike":247.5,"bid":8.5,"ask":9.05,"impliedVolatility":0.29224340576171864,"openInterest":89},{"strike":250,"bid":7.15,"ask":7.35,"impliedVolatility":0.2974923767089843,"openInterest":575},{"strike":252.5,"bid":5.3,"ask":5.9,"impliedVolatility":0.3045723840332031,"openInterest":71},{"strike":255,"bid":4.3,"ask":4.5,"impliedVolatility":0.3001778967285156,"openInterest":592},{"strike":257.5,"bid":3.2,"ask":3.4,"impliedVolatility":0.3011544494628906,"openInterest":85},{"strike":260,"bid":2.37,"ask":2.54,"impliedVolatility":0.30445031494140623,"openInterest":445},{"strike":262.5,"bid":1.63,"ask":1.96,"impliedVolatility":0.31555860229492183,"openInterest":162},{"strike":265,"bid":1.19,"ask":1.35,"impliedVolatility":0.3117744604492187,"openInterest":214},{"strike":267.5,"bid":0.82,"ask":1.04,"impliedVolatility":0.3237372314453124,"openInterest":77},{"strike":270,"bid":0.58,"ask":0.75,"impliedVolatility":0.3288641333007812,"openInterest":63},{"strike":272.5,"bid":0.4,"ask":0.53,"impliedVolatility":0.3327703442382813,"openInterest":318},{"strike":275,"bid":0.25,"ask":0.37,"impliedVolatility":0.3364324169921875,"openInterest":45},{"strike":280,"bid":0.1,"ask":0.18,"impliedVolatility":0.34570966796874997,"openInterest":161},{"strike":285,"bid":0.02,"ask":0.08,"impliedVolatility":0.3505924316406249,"openInterest":13},{"strike":290,"bid":0.01,"ask":0.14,"impliedVolatility":0.43066975585937506,"openInterest":21},{"strike":300,"bid":0,"ask":0.31,"impliedVolatility":0.532231240234375,"openInterest":54},{"strike":310,"bid":0,"ask":0.41,"impliedVolatility":0.647464462890625,"openInterest":23},{"strike":315,"bid":0,"ask":0.25,"impliedVolatility":0.6435582519531251,"openInterest":101}],"1784851200":[{"strike":140,"bid":112.75,"ask":116.25,"impliedVolatility":2.1591842895507813,"openInterest":17},{"strike":145,"bid":108,"ask":110.8,"impliedVolatility":1.888672431640625,"openInterest":15},{"strike":150,"bid":102.8,"ask":106.3,"impliedVolatility":1.958984580078125,"openInterest":14},{"strike":155,"bid":97.8,"ask":101.2,"impliedVolatility":1.8261727441406248,"openInterest":9},{"strike":160,"bid":92.8,"ask":94.55,"impliedVolatility":0.000010000000000000003,"openInterest":7},{"strike":165,"bid":87.85,"ask":91,"impliedVolatility":1.5727560424804685,"openInterest":2},{"strike":170,"bid":83.55,"ask":86.05,"impliedVolatility":1.4951197119140622,"openInterest":22},{"strike":180,"bid":73,"ask":76.05,"impliedVolatility":1.3173862255859374,"openInterest":30},{"strike":185,"bid":67.85,"ask":71.25,"impliedVolatility":1.2773473632812498,"openInterest":2},{"strike":195,"bid":57.85,"ask":61.1,"impliedVolatility":1.0747116577148441,"openInterest":15},{"strike":200,"bid":53.8,"ask":54.8,"impliedVolatility":0.000010000000000000003,"openInterest":262},{"strike":205,"bid":48.8,"ask":49.8,"impliedVolatility":0.000010000000000000003,"openInterest":93},{"strike":210,"bid":43.85,"ask":44.9,"impliedVolatility":0.000010000000000000003,"openInterest":94},{"strike":215,"bid":38.75,"ask":39.85,"impliedVolatility":0.000010000000000000003,"openInterest":173},{"strike":220,"bid":33.95,"ask":34.8,"impliedVolatility":0.000010000000000000003,"openInterest":1644},{"strike":222.5,"bid":31.3,"ask":32.4,"impliedVolatility":0.000010000000000000003,"openInterest":4},{"strike":225,"bid":29.05,"ask":29.9,"impliedVolatility":0.000010000000000000003,"openInterest":434},{"strike":227.5,"bid":26.55,"ask":27.6,"impliedVolatility":0.3544986425781249,"openInterest":83},{"strike":230,"bid":24.1,"ask":25.2,"impliedVolatility":0.358404853515625,"openInterest":775},{"strike":232.5,"bid":21.85,"ask":22.55,"impliedVolatility":0.27539787109374997,"openInterest":181},{"strike":235,"bid":19.35,"ask":20.5,"impliedVolatility":0.3544986425781249,"openInterest":706},{"strike":237.5,"bid":17.1,"ask":18.25,"impliedVolatility":0.3537662280273437,"openInterest":88},{"strike":240,"bid":15.65,"ask":15.8,"impliedVolatility":0.32141791870117187,"openInterest":2811},{"strike":242.5,"bid":13.1,"ask":13.85,"impliedVolatility":0.3363103479003906,"openInterest":697},{"strike":245,"bid":11.2,"ask":11.8,"impliedVolatility":0.3288641333007812,"openInterest":5323},{"strike":247.5,"bid":9.65,"ask":9.95,"impliedVolatility":0.32691102783203124,"openInterest":5988},{"strike":250,"bid":8.1,"ask":8.2,"impliedVolatility":0.32141791870117187,"openInterest":9920},{"strike":252.5,"bid":6.6,"ask":6.8,"impliedVolatility":0.3272772351074219,"openInterest":775},{"strike":255,"bid":5.35,"ask":5.4,"impliedVolatility":0.3219061950683593,"openInterest":3891},{"strike":257.5,"bid":4.25,"ask":4.4,"impliedVolatility":0.32971861694335935,"openInterest":912},{"strike":260,"bid":3.3,"ask":3.4,"impliedVolatility":0.3270330969238281,"openInterest":9763},{"strike":262.5,"bid":2.56,"ask":2.62,"impliedVolatility":0.3278875805664062,"openInterest":1636},{"strike":265,"bid":1.89,"ask":2.01,"impliedVolatility":0.33045103149414057,"openInterest":11198},{"strike":267.5,"bid":1.43,"ask":1.53,"impliedVolatility":0.33350275878906255,"openInterest":314},{"strike":270,"bid":1.08,"ask":1.15,"impliedVolatility":0.3364324169921875,"openInterest":5204},{"strike":272.5,"bid":0.77,"ask":0.85,"impliedVolatility":0.33850759155273435,"openInterest":322},{"strike":275,"bid":0.6,"ask":0.62,"impliedVolatility":0.3403386279296875,"openInterest":4372},{"strike":280,"bid":0.27,"ask":0.31,"impliedVolatility":0.34229173339843744,"openInterest":3882},{"strike":285,"bid":0.13,"ask":0.16,"impliedVolatility":0.3491276025390625,"openInterest":905},{"strike":290,"bid":0.02,"ask":0.1,"impliedVolatility":0.366217275390625,"openInterest":1087},{"strike":295,"bid":0.03,"ask":0.05,"impliedVolatility":0.3711000390625,"openInterest":531},{"strike":300,"bid":0.01,"ask":0.03,"impliedVolatility":0.38477177734374995,"openInterest":747},{"strike":305,"bid":0.01,"ask":0.09,"impliedVolatility":0.47852083984375,"openInterest":73},{"strike":310,"bid":0,"ask":0.21,"impliedVolatility":0.52539537109375,"openInterest":38},{"strike":315,"bid":0,"ask":0.22,"impliedVolatility":0.5664105859375,"openInterest":22},{"strike":320,"bid":0,"ask":0.06,"impliedVolatility":0.51562984375,"openInterest":544},{"strike":325,"bid":0,"ask":0.22,"impliedVolatility":0.6367223828125,"openInterest":29},{"strike":330,"bid":0,"ask":0.01,"impliedVolatility":0.523442265625,"openInterest":114},{"strike":335,"bid":0,"ask":0.07,"impliedVolatility":0.6171913281250001,"openInterest":4},{"strike":340,"bid":0,"ask":0.22,"impliedVolatility":0.73633076171875,"openInterest":75},{"strike":350,"bid":0,"ask":0.01,"impliedVolatility":0.5937540625000001,"openInterest":7},{"strike":365,"bid":0,"ask":0.22,"impliedVolatility":0.8906260937499999,"openInterest":1},{"strike":370,"bid":0,"ask":0.22,"impliedVolatility":0.91992267578125,"openInterest":3},{"strike":375,"bid":0,"ask":0.12,"impliedVolatility":0.8867198828124999,"openInterest":15},{"strike":380,"bid":0,"ask":0.01,"impliedVolatility":0.73437765625,"openInterest":5}],"1785456000":[{"strike":140,"bid":113.45,"ask":116.35,"impliedVolatility":1.6811539379882814,"openInterest":11},{"strike":145,"bid":108.2,"ask":111.35,"impliedVolatility":1.5961934252929684,"openInterest":37},{"strike":150,"bid":103.2,"ask":105.95,"impliedVolatility":1.4150419873046878,"openInterest":43},{"strike":155,"bid":97.95,"ask":101.4,"impliedVolatility":1.4443387158203125,"openInterest":31},{"strike":160,"bid":93.25,"ask":95.25,"impliedVolatility":1.0283251708984378,"openInterest":17},{"strike":165,"bid":88.45,"ask":90.25,"impliedVolatility":0.9677737597656251,"openInterest":11},{"strike":170,"bid":83.75,"ask":85.25,"impliedVolatility":0.9091805957031249,"openInterest":33},{"strike":175,"bid":78.5,"ask":80.25,"impliedVolatility":0.851563984375,"openInterest":11},{"strike":180,"bid":73.7,"ask":75.3,"impliedVolatility":0.8159198095703124,"openInterest":35},{"strike":185,"bid":68.75,"ask":70.35,"impliedVolatility":0.7773459765625,"openInterest":8},{"strike":190,"bid":63.65,"ask":65.45,"impliedVolatility":0.7509790527343749,"openInterest":20},{"strike":195,"bid":58.7,"ask":60.55,"impliedVolatility":0.7187528125,"openInterest":4},{"strike":200,"bid":53.7,"ask":55.65,"impliedVolatility":0.6826203613281252,"openInterest":39},{"strike":205,"bid":48.8,"ask":50.8,"impliedVolatility":0.6518589501953126,"openInterest":46},{"strike":210,"bid":44,"ask":45.65,"impliedVolatility":0.5686078295898438,"openInterest":95},{"strike":215,"bid":39.35,"ask":41.2,"impliedVolatility":0.5891154370117189,"openInterest":159},{"strike":220,"bid":34.9,"ask":36.65,"impliedVolatility":0.5753216296386718,"openInterest":255},{"strike":225,"bid":30.4,"ask":31.5,"impliedVolatility":0.49646499633789065,"openInterest":964},{"strike":230,"bid":26.3,"ask":27.25,"impliedVolatility":0.4939015454101563,"openInterest":2933},{"strike":235,"bid":22.25,"ask":23.25,"impliedVolatility":0.4910939562988281,"openInterest":2067},{"strike":240,"bid":18.6,"ask":19.45,"impliedVolatility":0.48303739624023445,"openInterest":2984},{"strike":245,"bid":15.6,"ask":15.95,"impliedVolatility":0.4744315252685547,"openInterest":1798},{"strike":250,"bid":12.7,"ask":13.05,"impliedVolatility":0.4777884252929688,"openInterest":6554},{"strike":255,"bid":10.1,"ask":10.4,"impliedVolatility":0.47485876708984376,"openInterest":2580},{"strike":260,"bid":7.95,"ask":8.25,"impliedVolatility":0.4774222180175781,"openInterest":4327},{"strike":265,"bid":6.05,"ask":6.45,"impliedVolatility":0.4796804962158203,"openInterest":3519},{"strike":270,"bid":4.7,"ask":4.9,"impliedVolatility":0.4779104943847656,"openInterest":3207},{"strike":275,"bid":3.45,"ask":3.7,"impliedVolatility":0.4788870471191406,"openInterest":2641},{"strike":280,"bid":2.54,"ask":2.8,"impliedVolatility":0.48291532714843755,"openInterest":2300},{"strike":285,"bid":1.9,"ask":2.04,"impliedVolatility":0.4823049816894531,"openInterest":1835},{"strike":290,"bid":1.37,"ask":1.48,"impliedVolatility":0.48328153442382815,"openInterest":736},{"strike":295,"bid":0.98,"ask":1.13,"impliedVolatility":0.4919484399414063,"openInterest":234},{"strike":300,"bid":0.7,"ask":0.81,"impliedVolatility":0.49341326904296884,"openInterest":2320},{"strike":305,"bid":0.46,"ask":0.61,"impliedVolatility":0.5009815527343751,"openInterest":265},{"strike":310,"bid":0.22,"ask":0.47,"impliedVolatility":0.5102588037109376,"openInterest":164},{"strike":315,"bid":0.12,"ask":0.41,"impliedVolatility":0.5302781347656251,"openInterest":50},{"strike":320,"bid":0.15,"ask":0.22,"impliedVolatility":0.508793974609375,"openInterest":89},{"strike":325,"bid":0.08,"ask":0.16,"impliedVolatility":0.5136767382812499,"openInterest":72},{"strike":330,"bid":0.01,"ask":0.36,"impliedVolatility":0.551762294921875,"openInterest":21},{"strike":335,"bid":0.02,"ask":0.16,"impliedVolatility":0.5273484765625001,"openInterest":20},{"strike":340,"bid":0.01,"ask":0.16,"impliedVolatility":0.5478560839843751,"openInterest":24},{"strike":345,"bid":0.01,"ask":0.19,"impliedVolatility":0.5830119824218749,"openInterest":85},{"strike":350,"bid":0.01,"ask":0.2,"impliedVolatility":0.6103554589843752,"openInterest":82},{"strike":355,"bid":0.01,"ask":0.02,"impliedVolatility":0.5195360546875,"openInterest":165}],"1786060800":[{"strike":140,"bid":113,"ask":116.5,"impliedVolatility":1.4448269946289063,"openInterest":4},{"strike":145,"bid":108,"ask":111.65,"impliedVolatility":1.3994170654296876,"openInterest":38},{"strike":150,"bid":103.1,"ask":106.55,"impliedVolatility":1.3105503222656247,"openInterest":15},{"strike":155,"bid":98.15,"ask":101.7,"impliedVolatility":1.2663610900878903,"openInterest":10},{"strike":160,"bid":93.8,"ask":95.45,"impliedVolatility":0.93945373046875,"openInterest":7},{"strike":165,"bid":89,"ask":90.55,"impliedVolatility":0.9135750830078125,"openInterest":4},{"strike":170,"bid":84.05,"ask":85.5,"impliedVolatility":0.8457046679687499,"openInterest":2},{"strike":180,"bid":74.15,"ask":75.8,"impliedVolatility":0.8061542822265625,"openInterest":1},{"strike":185,"bid":69.15,"ask":70.8,"impliedVolatility":0.752932158203125,"openInterest":10},{"strike":190,"bid":64.2,"ask":65.8,"impliedVolatility":0.7004424487304688,"openInterest":28},{"strike":195,"bid":59.2,"ask":60.65,"impliedVolatility":0.6235389208984375,"openInterest":4},{"strike":200,"bid":54.3,"ask":55.8,"impliedVolatility":0.5986368261718751,"openInterest":37},{"strike":205,"bid":49.6,"ask":51.25,"impliedVolatility":0.6059609716796877,"openInterest":28},{"strike":210,"bid":44.65,"ask":46.25,"impliedVolatility":0.5529829858398438,"openInterest":18},{"strike":215,"bid":40.3,"ask":41.6,"impliedVolatility":0.534184345703125,"openInterest":19},{"strike":220,"bid":35.45,"ask":37.1,"impliedVolatility":0.5200243310546875,"openInterest":370},{"strike":225,"bid":31.1,"ask":32.75,"impliedVolatility":0.5072070764160157,"openInterest":74},{"strike":230,"bid":27.1,"ask":28.6,"impliedVolatility":0.4963429272460938,"openInterest":228},{"strike":235,"bid":23.45,"ask":24.5,"impliedVolatility":0.4779104943847656,"openInterest":2285},{"strike":240,"bid":20.05,"ask":20.95,"impliedVolatility":0.47510290527343746,"openInterest":1593},{"strike":245,"bid":17.2,"ask":17.45,"impliedVolatility":0.462041512451172,"openInterest":1873},{"strike":250,"bid":14.2,"ask":14.55,"impliedVolatility":0.4611870288085938,"openInterest":1502},{"strike":255,"bid":11.6,"ask":11.9,"impliedVolatility":0.4572197833251954,"openInterest":2004},{"strike":260,"bid":9.4,"ask":9.75,"impliedVolatility":0.45978323425292966,"openInterest":2159},{"strike":265,"bid":7.5,"ask":7.8,"impliedVolatility":0.4577690942382813,"openInterest":1765},{"strike":270,"bid":5.9,"ask":6.2,"impliedVolatility":0.4577690942382813,"openInterest":2367},{"strike":275,"bid":4.6,"ask":4.9,"impliedVolatility":0.4592339233398438,"openInterest":3028},{"strike":280,"bid":3.6,"ask":3.75,"impliedVolatility":0.4563042651367188,"openInterest":2602},{"strike":285,"bid":2.71,"ask":2.98,"impliedVolatility":0.4622856506347657,"openInterest":1351},{"strike":290,"bid":2.12,"ask":2.18,"impliedVolatility":0.45642633422851564,"openInterest":1810},{"strike":295,"bid":1.57,"ask":1.83,"impliedVolatility":0.47119669433593747,"openInterest":769},{"strike":300,"bid":1.2,"ask":1.39,"impliedVolatility":0.47241738525390625,"openInterest":829},{"strike":305,"bid":0.86,"ask":1.09,"impliedVolatility":0.47803256347656253,"openInterest":120},{"strike":310,"bid":0.63,"ask":0.85,"impliedVolatility":0.48291532714843755,"openInterest":181},{"strike":315,"bid":0.5,"ask":0.67,"impliedVolatility":0.4887746435546876,"openInterest":20},{"strike":320,"bid":0.36,"ask":0.5,"impliedVolatility":0.4897511962890626,"openInterest":63},{"strike":325,"bid":0.28,"ask":0.37,"impliedVolatility":0.4907277490234375,"openInterest":52},{"strike":330,"bid":0.16,"ask":0.35,"impliedVolatility":0.5107470800781251,"openInterest":34},{"strike":340,"bid":0.09,"ask":0.16,"impliedVolatility":0.499028447265625,"openInterest":20},{"strike":345,"bid":0.09,"ask":0.16,"impliedVolatility":0.5039112109375,"openInterest":132}],"1786665600":[{"strike":165,"bid":88.4,"ask":91.85,"impliedVolatility":0.6621127539062501,"openInterest":2},{"strike":180,"bid":73.65,"ask":77.05,"impliedVolatility":0.6176796044921876,"openInterest":40},{"strike":190,"bid":64.05,"ask":66.8,"impliedVolatility":0.5507857421875001,"openInterest":50},{"strike":195,"bid":59.2,"ask":61.95,"impliedVolatility":0.5366257275390626,"openInterest":50},{"strike":200,"bid":54.1,"ask":57.2,"impliedVolatility":0.5053760400390624,"openInterest":99},{"strike":205,"bid":49.8,"ask":52.35,"impliedVolatility":0.514653291015625,"openInterest":46},{"strike":210,"bid":45,"ask":47.9,"impliedVolatility":0.5050098327636718,"openInterest":104},{"strike":215,"bid":40.15,"ask":42.8,"impliedVolatility":0.5550581604003908,"openInterest":95},{"strike":220,"bid":35.85,"ask":38.6,"impliedVolatility":0.5484664294433594,"openInterest":28},{"strike":225,"bid":31.5,"ask":34.3,"impliedVolatility":0.5285691674804689,"openInterest":37},{"strike":230,"bid":27.95,"ask":30.2,"impliedVolatility":0.5120288055419921,"openInterest":86},{"strike":235,"bid":24.1,"ask":25.7,"impliedVolatility":0.47192910888671874,"openInterest":69},{"strike":240,"bid":20.9,"ask":22.35,"impliedVolatility":0.47241738525390625,"openInterest":128},{"strike":245,"bid":18,"ask":19.15,"impliedVolatility":0.46808393249511715,"openInterest":2192},{"strike":250,"bid":15.15,"ask":15.5,"impliedVolatility":0.4386652813720704,"openInterest":175},{"strike":255,"bid":12.65,"ask":13,"impliedVolatility":0.43945873046875,"openInterest":206},{"strike":260,"bid":10.35,"ask":10.8,"impliedVolatility":0.4401301104736328,"openInterest":1396},{"strike":265,"bid":8.5,"ask":8.85,"impliedVolatility":0.43933666137695315,"openInterest":1034},{"strike":270,"bid":6.7,"ask":7.2,"impliedVolatility":0.43945873046875,"openInterest":1522},{"strike":275,"bid":5.45,"ask":5.75,"impliedVolatility":0.437505625,"openInterest":1611},{"strike":280,"bid":4.25,"ask":4.6,"impliedVolatility":0.4382380395507813,"openInterest":2026},{"strike":285,"bid":3.5,"ask":3.5,"impliedVolatility":0.43195148132324224,"openInterest":5764},{"strike":290,"bid":2.59,"ask":2.91,"impliedVolatility":0.44165597412109375,"openInterest":548},{"strike":295,"bid":1.99,"ask":2.27,"impliedVolatility":0.4420221813964844,"openInterest":38},{"strike":300,"bid":1.58,"ask":1.77,"impliedVolatility":0.44324287231445314,"openInterest":286},{"strike":305,"bid":1.17,"ask":1.46,"impliedVolatility":0.4514215014648438,"openInterest":84},{"strike":310,"bid":0.99,"ask":1.1,"impliedVolatility":0.4497125341796875,"openInterest":111},{"strike":320,"bid":0.49,"ask":0.74,"impliedVolatility":0.46411668701171876,"openInterest":40},{"strike":325,"bid":0.41,"ask":0.58,"impliedVolatility":0.46680220703125,"openInterest":11},{"strike":330,"bid":0.25,"ask":0.49,"impliedVolatility":0.47559118164062497,"openInterest":10},{"strike":335,"bid":0.18,"ask":0.37,"impliedVolatility":0.47510290527343746,"openInterest":10},{"strike":340,"bid":0.12,"ask":0.34,"impliedVolatility":0.4897511962890626,"openInterest":3},{"strike":345,"bid":0.1,"ask":0.2,"impliedVolatility":0.4721732470703125,"openInterest":1}],"1787270400":[{"strike":110,"bid":143.15,"ask":146.15,"impliedVolatility":1.4697292138671876,"openInterest":501},{"strike":115,"bid":138.15,"ask":141.7,"impliedVolatility":1.5083032397460938,"openInterest":85},{"strike":120,"bid":133.45,"ask":136.2,"impliedVolatility":1.343265002441406,"openInterest":1428},{"strike":125,"bid":128.65,"ask":130.55,"impliedVolatility":1.1220747021484376,"openInterest":212},{"strike":130,"bid":123.3,"ask":126.25,"impliedVolatility":1.2260780883789062,"openInterest":183},{"strike":135,"bid":118.3,"ask":121.3,"impliedVolatility":1.1743205346679688,"openInterest":132},{"strike":140,"bid":113.7,"ask":116.3,"impliedVolatility":0.6796907031250001,"openInterest":155},{"strike":145,"bid":109.3,"ask":110.65,"impliedVolatility":0.5820354296875,"openInterest":93},{"strike":150,"bid":104.15,"ask":105.55,"impliedVolatility":0.8627943408203125,"openInterest":129},{"strike":155,"bid":99.25,"ask":100.6,"impliedVolatility":0.8271501660156249,"openInterest":257},{"strike":160,"bid":94.45,"ask":95.8,"impliedVolatility":0.6357458300781251,"openInterest":166},{"strike":165,"bid":89.5,"ask":90.7,"impliedVolatility":0.584965087890625,"openInterest":127},{"strike":170,"bid":84.6,"ask":85.95,"impliedVolatility":0.6152382226562501,"openInterest":144},{"strike":175,"bid":79.65,"ask":80.85,"impliedVolatility":0.569340244140625,"openInterest":1827},{"strike":180,"bid":74.75,"ask":75.95,"impliedVolatility":0.5576216113281252,"openInterest":1595},{"strike":185,"bid":69.9,"ask":70.8,"impliedVolatility":0.5195360546875,"openInterest":280},{"strike":190,"bid":64.85,"ask":65.95,"impliedVolatility":0.5759319750976561,"openInterest":535},{"strike":195,"bid":60.15,"ask":61.1,"impliedVolatility":0.5510298803710938,"openInterest":798},{"strike":200,"bid":55.2,"ask":56.3,"impliedVolatility":0.5286912365722658,"openInterest":2155},{"strike":205,"bid":50.45,"ask":51.6,"impliedVolatility":0.5116015637207032,"openInterest":1387},{"strike":210,"bid":46.05,"ask":46.95,"impliedVolatility":0.4936574072265626,"openInterest":1648},{"strike":215,"bid":41.55,"ask":42.45,"impliedVolatility":0.4804739453125,"openInterest":1167},{"strike":220,"bid":37.2,"ask":38.1,"impliedVolatility":0.4695487615966797,"openInterest":3366},{"strike":225,"bid":33.05,"ask":33.9,"impliedVolatility":0.4591118542480469,"openInterest":2891},{"strike":230,"bid":29.35,"ask":29.7,"impliedVolatility":0.4417780432128906,"openInterest":4251},{"strike":235,"bid":25.45,"ask":26.2,"impliedVolatility":0.44507390869140623,"openInterest":4287},{"strike":240,"bid":22.2,"ask":22.55,"impliedVolatility":0.4335994140625,"openInterest":10632},{"strike":245,"bid":19.05,"ask":19.4,"impliedVolatility":0.4309138940429688,"openInterest":6937},{"strike":250,"bid":16.3,"ask":16.45,"impliedVolatility":0.42578699218750005,"openInterest":29033},{"strike":255,"bid":13.7,"ask":13.95,"impliedVolatility":0.42590906127929695,"openInterest":17009},{"strike":260,"bid":11.45,"ask":11.6,"impliedVolatility":0.42200285034179685,"openInterest":43058},{"strike":265,"bid":9.5,"ask":9.65,"impliedVolatility":0.4218197467041016,"openInterest":9449},{"strike":270,"bid":7.7,"ask":7.9,"impliedVolatility":0.41974457214355465,"openInterest":60073},{"strike":275,"bid":6.25,"ask":6.45,"impliedVolatility":0.4194393994140625,"openInterest":13240},{"strike":280,"bid":5.1,"ask":5.25,"impliedVolatility":0.42023284851074216,"openInterest":29986},{"strike":285,"bid":4.05,"ask":4.2,"impliedVolatility":0.41919526123046874,"openInterest":21566},{"strike":290,"bid":3.2,"ask":3.35,"impliedVolatility":0.41919526123046874,"openInterest":15232},{"strike":295,"bid":2.56,"ask":2.7,"impliedVolatility":0.42163664306640625,"openInterest":29085},{"strike":300,"bid":2.04,"ask":2.11,"impliedVolatility":0.4206600903320313,"openInterest":20044},{"strike":305,"bid":1.61,"ask":1.66,"impliedVolatility":0.4215145739746094,"openInterest":4502},{"strike":310,"bid":1.27,"ask":1.36,"impliedVolatility":0.4270076831054688,"openInterest":29464},{"strike":315,"bid":1.01,"ask":1.09,"impliedVolatility":0.43018147949218755,"openInterest":5368},{"strike":320,"bid":0.79,"ask":0.85,"impliedVolatility":0.4309138940429688,"openInterest":44738},{"strike":325,"bid":0.63,"ask":0.69,"impliedVolatility":0.43530838134765626,"openInterest":3317},{"strike":330,"bid":0.5,"ask":0.57,"impliedVolatility":0.44116769775390624,"openInterest":2354},{"strike":335,"bid":0.39,"ask":0.47,"impliedVolatility":0.446294599609375,"openInterest":7178},{"strike":340,"bid":0.31,"ask":0.35,"impliedVolatility":0.44434149414062496,"openInterest":2466},{"strike":345,"bid":0.21,"ask":0.33,"impliedVolatility":0.4585015087890626,"openInterest":94},{"strike":350,"bid":0.19,"ask":0.22,"impliedVolatility":0.44922425781249997,"openInterest":39339},{"strike":355,"bid":0.12,"ask":0.2,"impliedVolatility":0.459966337890625,"openInterest":40},{"strike":360,"bid":0.08,"ask":0.14,"impliedVolatility":0.45508357421875,"openInterest":1194},{"strike":365,"bid":0.08,"ask":0.16,"impliedVolatility":0.47852083984375,"openInterest":29},{"strike":370,"bid":0.05,"ask":0.11,"impliedVolatility":0.471684970703125,"openInterest":39099},{"strike":375,"bid":0.03,"ask":0.12,"impliedVolatility":0.49121602539062503,"openInterest":235},{"strike":380,"bid":0.04,"ask":0.09,"impliedVolatility":0.4892629199218751,"openInterest":10018},{"strike":390,"bid":0.02,"ask":0.05,"impliedVolatility":0.48633326171875,"openInterest":4327}],"1787875200":[{"strike":170,"bid":83.85,"ask":87.05,"impliedVolatility":0.6074258007812501,"openInterest":1},{"strike":200,"bid":55.1,"ask":57.8,"impliedVolatility":0.5943644079589845,"openInterest":1},{"strike":205,"bid":50.6,"ask":53.15,"impliedVolatility":0.5697064514160157,"openInterest":3},{"strike":220,"bid":37.35,"ask":39.8,"impliedVolatility":0.5083056982421875,"openInterest":3},{"strike":230,"bid":29.05,"ask":31.7,"impliedVolatility":0.4797415307617187,"openInterest":16},{"strike":235,"bid":25.75,"ask":27.5,"impliedVolatility":0.4529473651123047,"openInterest":9},{"strike":240,"bid":22.05,"ask":24.1,"impliedVolatility":0.4472101177978516,"openInterest":117},{"strike":245,"bid":19.55,"ask":20.95,"impliedVolatility":0.4420221813964844,"openInterest":37},{"strike":250,"bid":16.8,"ask":17.5,"impliedVolatility":0.4213314703369141,"openInterest":67},{"strike":255,"bid":14.4,"ask":14.95,"impliedVolatility":0.4194393994140625,"openInterest":51},{"strike":260,"bid":12.1,"ask":12.55,"impliedVolatility":0.4144345666503906,"openInterest":27},{"strike":265,"bid":10.1,"ask":10.6,"impliedVolatility":0.41480077392578124,"openInterest":16},{"strike":270,"bid":8.4,"ask":8.9,"impliedVolatility":0.41535008483886715,"openInterest":36},{"strike":275,"bid":6.9,"ask":7.2,"impliedVolatility":0.4089414575195312,"openInterest":53},{"strike":280,"bid":5.6,"ask":6.05,"impliedVolatility":0.41296973754882804,"openInterest":69},{"strike":285,"bid":4.6,"ask":5,"impliedVolatility":0.41431249755859373,"openInterest":37},{"strike":290,"bid":3.7,"ask":4,"impliedVolatility":0.41138283935546877,"openInterest":54},{"strike":295,"bid":3,"ask":3.3,"impliedVolatility":0.4141904284667969,"openInterest":113},{"strike":300,"bid":2.41,"ask":2.72,"impliedVolatility":0.4172421557617187,"openInterest":68},{"strike":310,"bid":1.53,"ask":1.8,"impliedVolatility":0.42090422851562503,"openInterest":4}],"1789689600":[{"strike":105,"bid":148.65,"ask":151.8,"impliedVolatility":0.9248054394531251,"openInterest":61},{"strike":110,"bid":143.7,"ask":146.85,"impliedVolatility":0.9003916210937499,"openInterest":38},{"strike":115,"bid":138.8,"ask":141.9,"impliedVolatility":0.8833019482421874,"openInterest":61},{"strike":120,"bid":133.8,"ask":136.7,"impliedVolatility":0.804689453125,"openInterest":228},{"strike":125,"bid":128.9,"ask":132.1,"impliedVolatility":0.8393570751953124,"openInterest":412},{"strike":130,"bid":123.85,"ask":127.05,"impliedVolatility":0.7851583984375,"openInterest":137},{"strike":135,"bid":118.95,"ask":122.15,"impliedVolatility":0.7683128637695313,"openInterest":146},{"strike":140,"bid":114,"ask":117.4,"impliedVolatility":0.7578149218750001,"openInterest":116},{"strike":145,"bid":109.05,"ask":112.25,"impliedVolatility":0.709963837890625,"openInterest":136},{"strike":150,"bid":104.15,"ask":107.1,"impliedVolatility":0.6679720703125002,"openInterest":366},{"strike":155,"bid":99.55,"ask":102.2,"impliedVolatility":0.6694368994140626,"openInterest":217},{"strike":160,"bid":94.35,"ask":97.3,"impliedVolatility":0.6259803027343751,"openInterest":443},{"strike":165,"bid":89.65,"ask":92.4,"impliedVolatility":0.6147499462890625,"openInterest":574},{"strike":170,"bid":85,"ask":87.55,"impliedVolatility":0.6052285571289064,"openInterest":318},{"strike":175,"bid":79.75,"ask":82.65,"impliedVolatility":0.5617719604492188,"openInterest":302},{"strike":180,"bid":75.05,"ask":77.8,"impliedVolatility":0.5468795312500001,"openInterest":567},{"strike":185,"bid":70.1,"ask":73.05,"impliedVolatility":0.523442265625,"openInterest":253},{"strike":190,"bid":66.1,"ask":67.45,"impliedVolatility":0.5026905200195313,"openInterest":1646},{"strike":195,"bid":61.2,"ask":62.75,"impliedVolatility":0.5256395092773438,"openInterest":437},{"strike":200,"bid":56.7,"ask":58.1,"impliedVolatility":0.50586431640625,"openInterest":3449},{"strike":205,"bid":51.95,"ask":53.55,"impliedVolatility":0.48871360900878913,"openInterest":1885},{"strike":210,"bid":47.9,"ask":49.15,"impliedVolatility":0.4751639398193359,"openInterest":3885},{"strike":215,"bid":43.5,"ask":44.8,"impliedVolatility":0.4602104760742188,"openInterest":1927},{"strike":220,"bid":39.75,"ask":40.65,"impliedVolatility":0.4489190850830078,"openInterest":14153},{"strike":225,"bid":35.5,"ask":36.65,"impliedVolatility":0.43836010864257813,"openInterest":4329},{"strike":230,"bid":32.1,"ask":32.9,"impliedVolatility":0.4309138940429688,"openInterest":6602},{"strike":235,"bid":28.45,"ask":29.2,"impliedVolatility":0.42017181396484377,"openInterest":3978},{"strike":240,"bid":25.2,"ask":25.95,"impliedVolatility":0.4164792239379882,"openInterest":7771},{"strike":245,"bid":22.4,"ask":22.85,"impliedVolatility":0.4112607702636719,"openInterest":13618},{"strike":250,"bid":19.65,"ask":19.9,"impliedVolatility":0.40454697021484376,"openInterest":12113},{"strike":255,"bid":17.15,"ask":17.35,"impliedVolatility":0.4019835192871094,"openInterest":9007},{"strike":260,"bid":14.8,"ask":15,"impliedVolatility":0.3988707574462891,"openInterest":12908},{"strike":265,"bid":12.65,"ask":12.9,"impliedVolatility":0.39642937561035163,"openInterest":6450},{"strike":270,"bid":10.95,"ask":11.1,"impliedVolatility":0.3959410992431641,"openInterest":22752},{"strike":275,"bid":9.25,"ask":9.45,"impliedVolatility":0.3942321319580079,"openInterest":7726},{"strike":280,"bid":7.85,"ask":8,"impliedVolatility":0.3927062683105469,"openInterest":16842},{"strike":285,"bid":6.6,"ask":6.8,"impliedVolatility":0.3930724755859375,"openInterest":7326},{"strike":290,"bid":5.55,"ask":5.8,"impliedVolatility":0.3947204083251954,"openInterest":11768},{"strike":295,"bid":4.65,"ask":4.9,"impliedVolatility":0.3952697192382813,"openInterest":3892},{"strike":300,"bid":4,"ask":4.05,"impliedVolatility":0.39331661376953125,"openInterest":18376},{"strike":305,"bid":3.25,"ask":3.5,"impliedVolatility":0.39789420471191406,"openInterest":4297},{"strike":310,"bid":2.74,"ask":2.88,"impliedVolatility":0.3963683410644532,"openInterest":2378},{"strike":315,"bid":2.28,"ask":2.43,"impliedVolatility":0.3983214465332031,"openInterest":2168},{"strike":320,"bid":1.89,"ask":2.05,"impliedVolatility":0.40027455200195317,"openInterest":6592},{"strike":325,"bid":1.58,"ask":1.71,"impliedVolatility":0.4012511047363281,"openInterest":4929},{"strike":330,"bid":1.32,"ask":1.42,"impliedVolatility":0.4019835192871094,"openInterest":2916},{"strike":335,"bid":1.09,"ask":1.17,"impliedVolatility":0.4023497265625,"openInterest":28},{"strike":340,"bid":0.92,"ask":1.01,"impliedVolatility":0.40650007568359375,"openInterest":2030},{"strike":350,"bid":0.63,"ask":0.69,"impliedVolatility":0.40796490478515623,"openInterest":12817},{"strike":360,"bid":0.43,"ask":0.52,"impliedVolatility":0.4162656030273437,"openInterest":6314},{"strike":370,"bid":0.3,"ask":0.37,"impliedVolatility":0.42017181396484377,"openInterest":6749},{"strike":375,"bid":0.24,"ask":0.29,"impliedVolatility":0.41797457031249996,"openInterest":324},{"strike":380,"bid":0.16,"ask":0.27,"impliedVolatility":0.42529871582031253,"openInterest":3716},{"strike":390,"bid":0.08,"ask":0.2,"impliedVolatility":0.43115803222656257,"openInterest":397},{"strike":400,"bid":0.09,"ask":0.13,"impliedVolatility":0.42969320312500003,"openInterest":674},{"strike":410,"bid":0.07,"ask":0.1,"impliedVolatility":0.436529072265625,"openInterest":1064}],"1792108800":[{"strike":100,"bid":154.35,"ask":157.15,"impliedVolatility":0.9584965087890623,"openInterest":133},{"strike":105,"bid":149.05,"ask":152.2,"impliedVolatility":0.8869640209960936,"openInterest":15},{"strike":110,"bid":144.15,"ask":147.3,"impliedVolatility":0.8642591699218749,"openInterest":33},{"strike":115,"bid":139.2,"ask":142.35,"impliedVolatility":0.8315446533203124,"openInterest":39},{"strike":120,"bid":134.3,"ask":137.45,"impliedVolatility":0.807619111328125,"openInterest":46},{"strike":125,"bid":129.35,"ask":132.55,"impliedVolatility":0.77929908203125,"openInterest":62},{"strike":130,"bid":124.45,"ask":127.6,"impliedVolatility":0.7512231909179687,"openInterest":63},{"strike":135,"bid":119.55,"ask":122.7,"impliedVolatility":0.7263210961914062,"openInterest":45},{"strike":140,"bid":114.65,"ask":117.8,"impliedVolatility":0.70117486328125,"openInterest":59},{"strike":145,"bid":109.75,"ask":112.9,"impliedVolatility":0.6760286303710938,"openInterest":59},{"strike":150,"bid":105.25,"ask":107.85,"impliedVolatility":0.6618686157226563,"openInterest":108},{"strike":155,"bid":100.2,"ask":103,"impliedVolatility":0.6313513427734375,"openInterest":1387},{"strike":160,"bid":95.15,"ask":98.15,"impliedVolatility":0.6014444152832032,"openInterest":108},{"strike":165,"bid":90.55,"ask":93.3,"impliedVolatility":0.5883830224609375,"openInterest":87},{"strike":170,"bid":85.6,"ask":88.5,"impliedVolatility":0.5634809277343751,"openInterest":103},{"strike":175,"bid":81.05,"ask":83.7,"impliedVolatility":0.5504195349121095,"openInterest":55},{"strike":180,"bid":76.4,"ask":78.4,"impliedVolatility":0.5189257092285156,"openInterest":124},{"strike":185,"bid":72.05,"ask":73.7,"impliedVolatility":0.5109912182617188,"openInterest":75},{"strike":190,"bid":67.25,"ask":69.05,"impliedVolatility":0.5297898583984376,"openInterest":381},{"strike":195,"bid":62.7,"ask":64.5,"impliedVolatility":0.5127001855468749,"openInterest":114},{"strike":200,"bid":58.45,"ask":60,"impliedVolatility":0.4959156854248047,"openInterest":315},{"strike":205,"bid":54.1,"ask":55.6,"impliedVolatility":0.48065704895019534,"openInterest":394},{"strike":210,"bid":49.5,"ask":51.35,"impliedVolatility":0.46802289794921875,"openInterest":243},{"strike":215,"bid":45.8,"ask":47.2,"impliedVolatility":0.4557549542236329,"openInterest":1216},{"strike":220,"bid":41.95,"ask":43.2,"impliedVolatility":0.4449518395996094,"openInterest":270},{"strike":225,"bid":38.25,"ask":39.35,"impliedVolatility":0.4349726913452149,"openInterest":524},{"strike":230,"bid":34.7,"ask":35.7,"impliedVolatility":0.4266719931030274,"openInterest":645},{"strike":235,"bid":31.25,"ask":32.3,"impliedVolatility":0.4206295730590821,"openInterest":1168},{"strike":240,"bid":28.3,"ask":28.75,"impliedVolatility":0.40799542205810546,"openInterest":1719},{"strike":245,"bid":25.1,"ask":25.9,"impliedVolatility":0.40650007568359375,"openInterest":2814},{"strike":250,"bid":22.75,"ask":23.05,"impliedVolatility":0.4011900701904296,"openInterest":5687},{"strike":255,"bid":20.2,"ask":20.45,"impliedVolatility":0.39716179016113284,"openInterest":1533},{"strike":260,"bid":17.9,"ask":18.1,"impliedVolatility":0.3942931665039063,"openInterest":2163},{"strike":265,"bid":15.75,"ask":15.95,"impliedVolatility":0.3916686810302734,"openInterest":3313},{"strike":270,"bid":13.85,"ask":14,"impliedVolatility":0.3893798855590821,"openInterest":2300},{"strike":275,"bid":12.15,"ask":12.3,"impliedVolatility":0.3885559191894531,"openInterest":11890},{"strike":280,"bid":10.6,"ask":10.75,"impliedVolatility":0.3873657455444336,"openInterest":4114},{"strike":285,"bid":9.15,"ask":9.35,"impliedVolatility":0.3860535028076171,"openInterest":1704},{"strike":290,"bid":7.95,"ask":8.15,"impliedVolatility":0.38587039916992183,"openInterest":3517},{"strike":295,"bid":6.85,"ask":7.15,"impliedVolatility":0.38733522827148437,"openInterest":1330},{"strike":300,"bid":5.9,"ask":6.2,"impliedVolatility":0.387152124633789,"openInterest":11115},{"strike":310,"bid":4.4,"ask":4.65,"impliedVolatility":0.3876404010009765,"openInterest":2819},{"strike":320,"bid":3.3,"ask":3.5,"impliedVolatility":0.3895324719238281,"openInterest":1885},{"strike":330,"bid":2.37,"ask":2.65,"impliedVolatility":0.39252316467285153,"openInterest":1302},{"strike":340,"bid":1.78,"ask":1.99,"impliedVolatility":0.39490351196289064,"openInterest":828},{"strike":350,"bid":1.31,"ask":1.47,"impliedVolatility":0.39600213378906257,"openInterest":1003},{"strike":360,"bid":1.01,"ask":1.12,"impliedVolatility":0.39990834472656256,"openInterest":796},{"strike":370,"bid":0.73,"ask":0.87,"impliedVolatility":0.40491317749023437,"openInterest":150},{"strike":375,"bid":0.63,"ask":0.74,"impliedVolatility":0.40479110839843746,"openInterest":292},{"strike":380,"bid":0.54,"ask":0.65,"impliedVolatility":0.40698835205078127,"openInterest":5468},{"strike":390,"bid":0.36,"ask":0.52,"impliedVolatility":0.41309180664062495,"openInterest":531},{"strike":400,"bid":0.31,"ask":0.41,"impliedVolatility":0.41797457031249996,"openInterest":500},{"strike":410,"bid":0.21,"ask":0.28,"impliedVolatility":0.4145566357421875,"openInterest":1347}],"1795132800":[{"strike":105,"bid":149.55,"ask":152.75,"impliedVolatility":0.8371598315429687,"openInterest":14},{"strike":110,"bid":0,"ask":0,"impliedVolatility":0.000010000000000000003,"openInterest":0},{"strike":115,"bid":139.8,"ask":142.95,"impliedVolatility":0.7850363293457032,"openInterest":34},{"strike":120,"bid":134.95,"ask":138.5,"impliedVolatility":0.7818625329589843,"openInterest":51},{"strike":125,"bid":130.05,"ask":133.55,"impliedVolatility":0.7512231909179687,"openInterest":76},{"strike":130,"bid":125.15,"ask":128.75,"impliedVolatility":0.7272976489257812,"openInterest":82},{"strike":135,"bid":120.4,"ask":123.5,"impliedVolatility":0.6921417504882813,"openInterest":80},{"strike":140,"bid":115.6,"ask":118.55,"impliedVolatility":0.667239655761719,"openInterest":101},{"strike":145,"bid":110.8,"ask":113.85,"impliedVolatility":0.6507603283691408,"openInterest":78},{"strike":150,"bid":106.1,"ask":108.9,"impliedVolatility":0.6286658227539064,"openInterest":115},{"strike":155,"bid":101.1,"ask":104.15,"impliedVolatility":0.6035195898437502,"openInterest":123},{"strike":160,"bid":96.6,"ask":99.35,"impliedVolatility":0.5903361279296876,"openInterest":156},{"strike":165,"bid":91.8,"ask":94.65,"impliedVolatility":0.5709271423339843,"openInterest":104},{"strike":170,"bid":87.65,"ask":89.4,"impliedVolatility":0.5532271240234375,"openInterest":161},{"strike":175,"bid":82.65,"ask":84.75,"impliedVolatility":0.5295457202148439,"openInterest":108},{"strike":180,"bid":78,"ask":80.15,"impliedVolatility":0.513554669189453,"openInterest":145},{"strike":185,"bid":74.1,"ask":75.65,"impliedVolatility":0.5113574255371094,"openInterest":164},{"strike":190,"bid":69,"ask":71.2,"impliedVolatility":0.5220384710693358,"openInterest":259},{"strike":195,"bid":64.75,"ask":66.85,"impliedVolatility":0.5084888018798828,"openInterest":105},{"strike":200,"bid":61.05,"ask":62.6,"impliedVolatility":0.49609878906250005,"openInterest":382},{"strike":205,"bid":56.95,"ask":58.45,"impliedVolatility":0.4846242944335938,"openInterest":369},{"strike":210,"bid":52.7,"ask":54.45,"impliedVolatility":0.47485876708984376,"openInterest":433},{"strike":215,"bid":49.05,"ask":50.55,"impliedVolatility":0.46533737792968755,"openInterest":1181},{"strike":220,"bid":45.6,"ask":46.8,"impliedVolatility":0.4568840933227539,"openInterest":1426},{"strike":225,"bid":41.55,"ask":43.2,"impliedVolatility":0.44922425781249997,"openInterest":429},{"strike":230,"bid":38.7,"ask":39.8,"impliedVolatility":0.44312080322265623,"openInterest":1727},{"strike":235,"bid":35.55,"ask":36.55,"impliedVolatility":0.43732252136230465,"openInterest":1035},{"strike":240,"bid":32.15,"ask":33.4,"impliedVolatility":0.4308528594970704,"openInterest":2272},{"strike":245,"bid":29.6,"ask":30.2,"impliedVolatility":0.4211178494262696,"openInterest":1635},{"strike":250,"bid":26.85,"ask":27.7,"impliedVolatility":0.42090422851562503,"openInterest":3124},{"strike":255,"bid":24.5,"ask":25.15,"impliedVolatility":0.4172116384887695,"openInterest":1211},{"strike":260,"bid":22.5,"ask":22.75,"impliedVolatility":0.4134885311889648,"openInterest":8976},{"strike":265,"bid":20.35,"ask":20.6,"impliedVolatility":0.41138283935546877,"openInterest":2070},{"strike":270,"bid":18.35,"ask":18.6,"impliedVolatility":0.40930766479492187,"openInterest":2233},{"strike":275,"bid":16.55,"ask":16.8,"impliedVolatility":0.4081785256958008,"openInterest":12355},{"strike":280,"bid":14.85,"ask":15.15,"impliedVolatility":0.40726300750732425,"openInterest":3297},{"strike":285,"bid":13.35,"ask":13.65,"impliedVolatility":0.40665266204833983,"openInterest":1943},{"strike":290,"bid":12.05,"ask":12.1,"impliedVolatility":0.402899037475586,"openInterest":4707},{"strike":295,"bid":10.5,"ask":10.9,"impliedVolatility":0.4032957620239258,"openInterest":1306},{"strike":300,"bid":9.6,"ask":9.85,"impliedVolatility":0.40451645294189453,"openInterest":5472},{"strike":305,"bid":8.6,"ask":8.85,"impliedVolatility":0.4048216256713867,"openInterest":2358},{"strike":310,"bid":7.6,"ask":7.95,"impliedVolatility":0.405279384765625,"openInterest":1869},{"strike":315,"bid":6.75,"ask":7.1,"impliedVolatility":0.40500472930908205,"openInterest":853},{"strike":320,"bid":6.05,"ask":6.35,"impliedVolatility":0.40515731567382807,"openInterest":2018},{"strike":325,"bid":5.4,"ask":5.7,"impliedVolatility":0.40595076477050784,"openInterest":2013},{"strike":330,"bid":4.8,"ask":5.15,"impliedVolatility":0.4076902493286133,"openInterest":984},{"strike":335,"bid":4.25,"ask":4.6,"impliedVolatility":0.40796490478515623,"openInterest":598},{"strike":340,"bid":3.8,"ask":4.1,"impliedVolatility":0.40808697387695314,"openInterest":2623},{"strike":350,"bid":3.05,"ask":3.3,"impliedVolatility":0.4099790447998046,"openInterest":1916},{"strike":360,"bid":2.37,"ask":2.64,"impliedVolatility":0.41138283935546877,"openInterest":700},{"strike":370,"bid":1.94,"ask":2.09,"impliedVolatility":0.4118711157226562,"openInterest":465},{"strike":375,"bid":1.65,"ask":1.94,"impliedVolatility":0.4158993957519531,"openInterest":131},{"strike":380,"bid":1.54,"ask":1.75,"impliedVolatility":0.41736422485351554,"openInterest":438},{"strike":390,"bid":1.19,"ask":1.42,"impliedVolatility":0.4198056066894531,"openInterest":390},{"strike":400,"bid":0.99,"ask":1.15,"impliedVolatility":0.42188078125,"openInterest":305},{"strike":410,"bid":0.79,"ask":0.96,"impliedVolatility":0.42615319946289065,"openInterest":415}]}}